{
"Ads": [
{

//  STATUS_APP = "0" must set 0 if your app still live on playstore
//  and STATUS_APP = "1" if your app "suspend"
//  fill LINK_REDIRECT with new link app
"STATUS_APP" : "0",
"LINK_REDIRECT" : "https://play.google.com/store/apps/details?id=com.package.name",

// memanggil data dari json "online" atau json "offline"
//  online atau offline
// jika online maka akan memanggil data mp3 wallpaper yang ada di json online kalian
//  jika offline maka akan mmanggil data mp3 wallpaper yang ada di json folder asset
// online offline huruf kecil
"MODE_MP3_ONLINE_OFFLINE" : "online",


"MODE_BACKUP_ADS" : true,
"MODE_NO_ADS" : false,
"ADS_ON_START" : false, // CTR NAIK PESAT
"ADS_ON_EXIT_DIALOG" : true, // CTR NAIK PESAT

"JSON_POPUP_WAIT" : "Server Json Ready . . .",
"MODE_NO_ADS_TRUE" : "Pro Version Actived",

// PENGATURAN IKLAN
// ADMOB      backup unity backup startapp
// FAN        backup unity backup startapp
// UNITY      backup startapp
// TAPDAQ     backup unity backup startapp
"MODE_TES_IKLAN_FAN_ADMOB_STARTAPP_UNITY" : true,
"PENGATURAN_IKLAN_BANNER" : "ADMOB",
"PENGATURAN_IKLAN_INTER" : "ADMOB",
"INTER_COUNT" : 5,

"ADMOB_INTER" : "ca-app-pub-3940256099942544/1033173712",
"ADMOB_BANNER" : "ca-app-pub-3940256099942544/6300978111",
"ADMOB_OPENADS" : "BIARKAN KOSONG",

"FAN_INTER" : "YOUR_PLACEMENT_ID",
"FAN_BANNER" : "YOUR_PLACEMENT_ID",

"UNITY_BANNER" : "banner",
"UNITY_INTERSTITIAL" : "interstitial",
"UNITY_GAME_ID" : "12345",

"STARTAPPID" : "123154",
"ENABLE_STRAP" : true,
"ENABLE_STRAP_SPLAHSCREEN" : false,

"TAPDAQ_APP_ID" : "6120a5b008fe6c2d735d6a78",
"TAPDAQ_CLIENT_KEY" : "fb5af849-b396-473b-a139-eecc9c3a4716",

//  Exit Dialog
//  Bantu Rating 5 bintang agar kami dapat terus memberikan informasi informasi terbaru
//  help give us a 5 star rating, so we keep the spirit of providing the latest updates
//  jika shre button "true" maka more button berubah fungsi menjadi share - more url hilang menjadi share
"EXIT_POPUP_DIALOG" : "
help give us a 5 star rating

so we keep the spirit of providing the latest updates

click rate now button
",
"RATE_BUTTON" : "Rate Now",
"LATER_BUTTON" : "Rate Later",
"ENABLE_SHARE_BUTTON" : true,
"SHARE_TXT" : "
this the best apps ever, ive try it and so awesome

you need to try download this too bro
",
"MORE_BUTTON" : "Share Via Whatsapp",
"URL_MORE_APPS" : "https://play.google.com/store/apps/details?id=com.package.name"

}
]
,"Mp3": [

 {    "name_mp3": "1999",    "link_mp3": "https://archive.org/download/unnokeng-80s/41 1999.mp3"  },
 
{    "name_mp3": "(I've Had) The Time Of My Life",    "link_mp3": "https://archive.org/download/unnokeng-80s/27 (I've Had) The Time Of My Life.mp3"  },
 
{    "name_mp3": "(Just Like) Starting Over",    "link_mp3": "https://archive.org/download/unnokeng-80s/04 (Just Like) Starting Over.mp3"  },
 
{    "name_mp3": "(Keep Feeling) Fascination",    "link_mp3": "https://archive.org/download/unnokeng-80s/33 (Keep Feeling) Fascination.mp3"  },
 
{    "name_mp3": "18 And Life",    "link_mp3": "https://archive.org/download/unnokeng-80s/61 18 And Life.mp3"  },
 
{    "name_mp3": "65 Love Affair",    "link_mp3": "https://archive.org/download/unnokeng-80s/39 '65 Love Affair.mp3"  },
 
{    "name_mp3": "867-5309_Jenny",    "link_mp3": "https://archive.org/download/unnokeng-80s/16 867-5309_Jenny.mp3"  },
 
{    "name_mp3": "9 To 5",    "link_mp3": "https://archive.org/download/unnokeng-80s/09 9 To 5.mp3"  },
 
{    "name_mp3": "A Woman Needs Love (Just Like You Do)",    "link_mp3": "https://archive.org/download/unnokeng-80s/16 A Woman Needs Love (Just Like You Do).mp3"  },
 
{    "name_mp3": "Addicted To Love",    "link_mp3": "https://archive.org/download/unnokeng-80s/10 Addicted To Love.mp3"  },
 
{    "name_mp3": "Africa",    "link_mp3": "https://archive.org/download/unnokeng-80s/24 Africa.mp3"  },
 
{    "name_mp3": "After All",    "link_mp3": "https://archive.org/download/unnokeng-80s/79 After All.mp3"  },
 
{    "name_mp3": "Against All Odds (Take A Look At Me Now)",    "link_mp3": "https://archive.org/download/unnokeng-80s/05 Against All Odds (Take A Look At Me Now).mp3"  },
 
{    "name_mp3": "Ain't Even Done With The Night",    "link_mp3": "https://archive.org/download/unnokeng-80s/63 Ain't Even Done With The Night.mp3"  },
 
{    "name_mp3": "All Night Long (All Night)",    "link_mp3": "https://archive.org/download/unnokeng-80s/12 All Night Long (All Night).mp3"  },
 
{    "name_mp3": "All Out Out of Love",    "link_mp3": "https://archive.org/download/unnokeng-80s/55 All Out Out of Love.mp3"  },
 
{    "name_mp3": "All This Time",    "link_mp3": "https://archive.org/download/unnokeng-80s/78 All This Time.mp3"  },
 
{    "name_mp3": "Allentown",    "link_mp3": "https://archive.org/download/unnokeng-80s/43 Allentown.mp3"  },
 
{    "name_mp3": "Almost Paradise",    "link_mp3": "https://archive.org/download/unnokeng-80s/59 Almost Paradise.mp3"  },
 
{    "name_mp3": "Alone",    "link_mp3": "https://archive.org/download/unnokeng-80s/02 Alone.mp3"  },
 
{    "name_mp3": "Always",    "link_mp3": "https://archive.org/download/unnokeng-80s/14 Always.mp3"  },
 
{    "name_mp3": "Always On My Mind",    "link_mp3": "https://archive.org/download/unnokeng-80s/22 Always On My Mind.mp3"  },
 
{    "name_mp3": "Always Something There To Remind Me",    "link_mp3": "https://archive.org/download/unnokeng-80s/46 Always Something There To Remind Me.mp3"  },
 
{    "name_mp3": "Amanda",    "link_mp3": "https://archive.org/download/unnokeng-80s/50 Amanda.mp3"  },
 
{    "name_mp3": "Another Brick in the Wall",    "link_mp3": "https://archive.org/download/unnokeng-80s/02 Another Brick in the Wall.mp3"  },
 
{    "name_mp3": "Arthur_s Theme (Best That You Can Do)",    "link_mp3": "https://archive.org/download/unnokeng-80s/64 Arthur_s Theme (Best That You Can Do).mp3"  },
 
{    "name_mp3": "At This Moment",    "link_mp3": "https://archive.org/download/unnokeng-80s/20 At This Moment.mp3"  },
 
{    "name_mp3": "Babe",    "link_mp3": "https://archive.org/download/unnokeng-80s/20 Babe.mp3"  },
 
{    "name_mp3": "Baby Come To Me",    "link_mp3": "https://archive.org/download/unnokeng-80s/08 Baby Come To Me.mp3"  },
 
{    "name_mp3": "Baby, I Love Your Way",    "link_mp3": "https://archive.org/download/unnokeng-80s/09 Baby%2C I Love Your Way.mp3"  },
 
{    "name_mp3": "Back On The Chain Gang",    "link_mp3": "https://archive.org/download/unnokeng-80s/26 Back On The Chain Gang.mp3"  },
 
{    "name_mp3": "Bad Medicine",    "link_mp3": "https://archive.org/download/unnokeng-80s/29 Bad Medicine.mp3"  },
 
{    "name_mp3": "Believe It Or Not (Greatest American Hero Theme)",    "link_mp3": "https://archive.org/download/unnokeng-80s/11 Believe It Or Not (Greatest American Hero Theme).mp3"  },
 
{    "name_mp3": "Biggest Part of Me",    "link_mp3": "https://archive.org/download/unnokeng-80s/27 Biggest Part of Me.mp3"  },
 
{    "name_mp3": "Billie Jean",    "link_mp3": "https://archive.org/download/unnokeng-80s/02 Billie Jean.mp3"  },
 
{    "name_mp3": "Blame It On The Rain",    "link_mp3": "https://archive.org/download/unnokeng-80s/21 Blame It On The Rain.mp3"  },
 
{    "name_mp3": "BlueBayou",    "link_mp3": "https://archive.org/download/unnokeng-80s/BlueBayou.mp3"  },
 
{    "name_mp3": "Borderline",    "link_mp3": "https://archive.org/download/unnokeng-80s/100 Borderline.mp3"  },
 
{    "name_mp3": "Boys Of Summer",    "link_mp3": "https://archive.org/download/unnokeng-80s/53 Boys Of Summer.mp3"  },
 
{    "name_mp3": "BrassInPocket",    "link_mp3": "https://archive.org/download/unnokeng-80s/41 BrassInPocket.mp3"  },
 
{    "name_mp3": "Breaking Us In Two",    "link_mp3": "https://archive.org/download/unnokeng-80s/99 Breaking Us In Two.mp3"  },
 
{    "name_mp3": "Broken Wings",    "link_mp3": "https://archive.org/download/unnokeng-80s/05 Broken Wings.mp3"  },
 
{    "name_mp3": "Bust A Move",    "link_mp3": "https://archive.org/download/unnokeng-80s/42 Bust A Move.mp3"  },
 
{    "name_mp3": "California Girls",    "link_mp3": "https://archive.org/download/unnokeng-80s/88 California Girls.mp3"  },
 
{    "name_mp3": "Call Me",    "link_mp3": "https://archive.org/download/unnokeng-80s/01 Call Me.mp3"  },
 
{    "name_mp3": "Candle In The Wind",    "link_mp3": "https://archive.org/download/unnokeng-80s/59 Candle In The Wind.mp3"  },
 
{    "name_mp3": "Can't Fight This Feeling",    "link_mp3": "https://archive.org/download/unnokeng-80s/13 Can't Fight This Feeling.mp3"  },
 
{    "name_mp3": "Careless Whisper",    "link_mp3": "https://archive.org/download/unnokeng-80s/01 Careless Whisper.mp3"  },
 
{    "name_mp3": "Carrie",    "link_mp3": "https://archive.org/download/unnokeng-80s/56 Carrie.mp3"  },
 
{    "name_mp3": "Cars",    "link_mp3": "https://archive.org/download/unnokeng-80s/12 Cars.mp3"  },
 
{    "name_mp3": "Cherish",    "link_mp3": "https://archive.org/download/unnokeng-80s/17 Cherish.mp3"  },
 
{    "name_mp3": "Cherish",    "link_mp3": "https://archive.org/download/unnokeng-80s/59 Cherish.mp3"  },
 
{    "name_mp3": "China Girl",    "link_mp3": "https://archive.org/download/unnokeng-80s/62 China Girl.mp3"  },
 
{    "name_mp3": "Come On Eileen",    "link_mp3": "https://archive.org/download/unnokeng-80s/13 Come On Eileen.mp3"  },
 
{    "name_mp3": "Crazy for You",    "link_mp3": "https://archive.org/download/unnokeng-80s/09 Crazy for You.mp3"  },
 
{    "name_mp3": "Crazy Little Thing Called Love",    "link_mp3": "https://archive.org/download/unnokeng-80s/06 Crazy Little Thing Called Love.mp3"  },
 
{    "name_mp3": "Cruel Summer",    "link_mp3": "https://archive.org/download/unnokeng-80s/73 Cruel Summer.mp3"  },
 
{    "name_mp3": "Cruisin'",    "link_mp3": "https://archive.org/download/unnokeng-80s/13 Cruisin'.mp3"  },
 
{    "name_mp3": "Crush on You",    "link_mp3": "https://archive.org/download/unnokeng-80s/52 Crush on You.mp3"  },
 
{    "name_mp3": "Dancing In The Dark",    "link_mp3": "https://archive.org/download/unnokeng-80s/14 Dancing In The Dark.mp3"  },
 
{    "name_mp3": "Danger Zone",    "link_mp3": "https://archive.org/download/unnokeng-80s/42 Danger Zone.mp3"  },
 
{    "name_mp3": "De Do Do Do, De Da Da Da",    "link_mp3": "https://archive.org/download/unnokeng-80s/57 De Do Do Do%2C De Da Da Da.mp3"  },
 
{    "name_mp3": "Didn't We Almost Have It All",    "link_mp3": "https://archive.org/download/unnokeng-80s/22 Didn't We Almost Have It All.mp3"  },
 
{    "name_mp3": "Dirty Diana",    "link_mp3": "https://archive.org/download/unnokeng-80s/57 Dirty Diana.mp3"  },
 
{    "name_mp3": "Do That To Me One More Time",    "link_mp3": "https://archive.org/download/unnokeng-80s/05 Do That To Me One More Time.mp3"  },
 
{    "name_mp3": "Do You Really Want To Hurt Me",    "link_mp3": "https://archive.org/download/unnokeng-80s/11 Do You Really Want To Hurt Me.mp3"  },
 
{    "name_mp3": "Don't Do Me Like That",    "link_mp3": "https://archive.org/download/unnokeng-80s/64 Don't Do Me Like That.mp3"  },
 
{    "name_mp3": "Don't Dream It's Over",    "link_mp3": "https://archive.org/download/unnokeng-80s/13 Don't Dream It's Over.mp3"  },
 
{    "name_mp3": "Don't Fall In Love With A Dreamer [feat Kem Carnes]",    "link_mp3": "https://archive.org/download/unnokeng-80s/31 Don't Fall In Love With A Dreamer [feat Kem Carnes].mp3"  },
 
{    "name_mp3": "Don't Get Me Wrong",    "link_mp3": "https://archive.org/download/unnokeng-80s/92 Don't Get Me Wrong.mp3"  },
 
{    "name_mp3": "Don't Let It End",    "link_mp3": "https://archive.org/download/unnokeng-80s/60 Don't Let It End.mp3"  },
 
{    "name_mp3": "Don't Mean Nothing",    "link_mp3": "https://archive.org/download/unnokeng-80s/54 Don't Mean Nothing.mp3"  },
 
{    "name_mp3": "Don't Stop Believin'",    "link_mp3": "https://archive.org/download/unnokeng-80s/73 Don't Stop Believin'.mp3"  },
 
{    "name_mp3": "Don't Wanna Lose You",    "link_mp3": "https://archive.org/download/unnokeng-80s/14 Don't Wanna Lose You.mp3"  },
 
{    "name_mp3": "Don't Worry Be Happy",    "link_mp3": "https://archive.org/download/unnokeng-80s/30 Don't Worry Be Happy.mp3"  },
 
{    "name_mp3": "Don't You Forget About Me",    "link_mp3": "https://archive.org/download/unnokeng-80s/16 Don't You Forget About Me.mp3"  },
 
{    "name_mp3": "Don't You Want Me",    "link_mp3": "https://archive.org/download/unnokeng-80s/06 Don't You Want Me.mp3"  },
 
{    "name_mp3": "DontKnowMuchfeatAaronNeville",    "link_mp3": "https://archive.org/download/unnokeng-80s/DontKnowMuchfeatAaronNeville.mp3"  },
 
{    "name_mp3": "Drive",    "link_mp3": "https://archive.org/download/unnokeng-80s/41 Drive.mp3"  },
 
{    "name_mp3": "Ebony and Ivory",    "link_mp3": "https://archive.org/download/unnokeng-80s/04 Ebony and Ivory.mp3"  },
 
{    "name_mp3": "Edge Of Seventeen",    "link_mp3": "https://archive.org/download/unnokeng-80s/100 Edge Of Seventeen.mp3"  },
 
{    "name_mp3": "Electric Avenue",    "link_mp3": "https://archive.org/download/unnokeng-80s/22 Electric Avenue.mp3"  },
 
{    "name_mp3": "Endless Love [feat Lionel Richie]",    "link_mp3": "https://archive.org/download/unnokeng-80s/02 Endless Love [feat Lionel Richie].mp3"  },
 
{    "name_mp3": "Endless Summer Nights",    "link_mp3": "https://archive.org/download/unnokeng-80s/36 Endless Summer Nights.mp3"  },
 
{    "name_mp3": "Escape (The Pina Colada Song)",    "link_mp3": "https://archive.org/download/unnokeng-80s/11 Escape (The Pina Colada Song).mp3"  },
 
{    "name_mp3": "Eternal Flame",    "link_mp3": "https://archive.org/download/unnokeng-80s/32 Eternal Flame.mp3"  },
 
{    "name_mp3": "Even The Nights Are Better",    "link_mp3": "https://archive.org/download/unnokeng-80s/37 Even The Nights Are Better.mp3"  },
 
{    "name_mp3": "Every Breath You Take",    "link_mp3": "https://archive.org/download/unnokeng-80s/01 Every Breath You Take.mp3"  },
 
{    "name_mp3": "Every Little Step",    "link_mp3": "https://archive.org/download/unnokeng-80s/48 Every Little Step.mp3"  },
 
{    "name_mp3": "Every Little Thing She Does Is Magic",    "link_mp3": "https://archive.org/download/unnokeng-80s/79 Every Little Thing She Does Is Magic.mp3"  },
 
{    "name_mp3": "Every Rose Has It's Thorn",    "link_mp3": "https://archive.org/download/unnokeng-80s/03 Every Rose Has It's Thorn.mp3"  },
 
{    "name_mp3": "Every Woman In The World",    "link_mp3": "https://archive.org/download/unnokeng-80s/27 Every Woman In The World.mp3"  },
 
{    "name_mp3": "Everybody Have Fun Tonight",    "link_mp3": "https://archive.org/download/unnokeng-80s/12 Everybody Have Fun Tonight.mp3"  },
 
{    "name_mp3": "Everybody Wants To Rule The World",    "link_mp3": "https://archive.org/download/unnokeng-80s/07 Everybody Wants To Rule The World.mp3"  },
 
{    "name_mp3": "Everything She Wants",    "link_mp3": "https://archive.org/download/unnokeng-80s/25 Everything She Wants.mp3"  },
 
{    "name_mp3": "Everytime You Go Away",    "link_mp3": "https://archive.org/download/unnokeng-80s/11 Everytime You Go Away.mp3"  },
 
{    "name_mp3": "Express Yourself",    "link_mp3": "https://archive.org/download/unnokeng-80s/55 Express Yourself.mp3"  },
 
{    "name_mp3": "Faithfully",    "link_mp3": "https://archive.org/download/unnokeng-80s/81 Faithfully.mp3"  },
 
{    "name_mp3": "Fall In Love With Me",    "link_mp3": "https://archive.org/download/unnokeng-80s/100 Fall In Love With Me.mp3"  },
 
{    "name_mp3": "Fame",    "link_mp3": "https://archive.org/download/unnokeng-80s/66 Fame.mp3"  },
 
{    "name_mp3": "Fast Car",    "link_mp3": "https://archive.org/download/unnokeng-80s/78 Fast Car.mp3"  },
 
{    "name_mp3": "Fight For Your Right (To Party",    "link_mp3": "https://archive.org/download/unnokeng-80s/98 Fight For Your Right (To Party.mp3"  },
 
{    "name_mp3": "Flashdance (What A Feeling)",    "link_mp3": "https://archive.org/download/unnokeng-80s/03 Flashdance (What A Feeling).mp3"  },
 
{    "name_mp3": "Footloose",    "link_mp3": "https://archive.org/download/unnokeng-80s/04 Footloose.mp3"  },
 
{    "name_mp3": "Forever Your Girl",    "link_mp3": "https://archive.org/download/unnokeng-80s/30 Forever Your Girl.mp3"  },
 
{    "name_mp3": "Funky Cold Medina",    "link_mp3": "https://archive.org/download/unnokeng-80s/65 Funky Cold Medina.mp3"  },
 
{    "name_mp3": "Funkytown",    "link_mp3": "https://archive.org/download/unnokeng-80s/08 Funkytown.mp3"  },
 
{    "name_mp3": "Girl You Know It's True",    "link_mp3": "https://archive.org/download/unnokeng-80s/08 Girl You Know It's True.mp3"  },
 
{    "name_mp3": "Girls Just Want To Have Fun",    "link_mp3": "https://archive.org/download/unnokeng-80s/15 Girls Just Want To Have Fun.mp3"  },
 
{    "name_mp3": "Giving You The Best That I Got",    "link_mp3": "https://archive.org/download/unnokeng-80s/10 Giving You The Best That I Got.mp3"  },
 
{    "name_mp3": "Giving You The Best That I Got",    "link_mp3": "https://archive.org/download/unnokeng-80s/14 Giving You The Best That I Got.mp3"  },
 
{    "name_mp3": "Glory Of Love",    "link_mp3": "https://archive.org/download/unnokeng-80s/14 Glory Of Love.mp3"  },
 
{    "name_mp3": "Greatest Love Of All",    "link_mp3": "https://archive.org/download/unnokeng-80s/11 Greatest Love Of All.mp3"  },
 
{    "name_mp3": "Groovy Kind Of Love",    "link_mp3": "https://archive.org/download/unnokeng-80s/27 Groovy Kind Of Love.mp3"  },
 
{    "name_mp3": "Guilty [feat Barry Gibb]",    "link_mp3": "https://archive.org/download/unnokeng-80s/29 Guilty [feat Barry Gibb].mp3"  },
 
{    "name_mp3": "Hard Habit To Break",    "link_mp3": "https://archive.org/download/unnokeng-80s/45 Hard Habit To Break.mp3"  },
 
{    "name_mp3": "Hard To Say I'm Sorry",    "link_mp3": "https://archive.org/download/unnokeng-80s/10 Hard To Say I'm Sorry.mp3"  },
 
{    "name_mp3": "Head Over Heels",    "link_mp3": "https://archive.org/download/unnokeng-80s/60 Head Over Heels.mp3"  },
 
{    "name_mp3": "Head Over Heels",    "link_mp3": "https://archive.org/download/unnokeng-80s/88 Head Over Heels.mp3"  },
 
{    "name_mp3": "Heart Breaker",    "link_mp3": "https://archive.org/download/unnokeng-80s/83 Heart Breaker.mp3"  },
 
{    "name_mp3": "Heart To Heart",    "link_mp3": "https://archive.org/download/unnokeng-80s/72 Heart To Heart.mp3"  },
 
{    "name_mp3": "Heartache Tonight",    "link_mp3": "https://archive.org/download/unnokeng-80s/47 Heartache Tonight.mp3"  },
 
{    "name_mp3": "Heartbreaker",    "link_mp3": "https://archive.org/download/unnokeng-80s/80 Heartbreaker.mp3"  },
 
{    "name_mp3": "Heat Of The Moment",    "link_mp3": "https://archive.org/download/unnokeng-80s/40 Heat Of The Moment.mp3"  },
 
{    "name_mp3": "Heat Of The Night",    "link_mp3": "https://archive.org/download/unnokeng-80s/84 Heat Of The Night.mp3"  },
 
{    "name_mp3": "HeatWave",    "link_mp3": "https://archive.org/download/unnokeng-80s/HeatWave.mp3"  },
 
{    "name_mp3": "Heaven",    "link_mp3": "https://archive.org/download/unnokeng-80s/24 Heaven.mp3"  },
 
{    "name_mp3": "Hello",    "link_mp3": "https://archive.org/download/unnokeng-80s/07 Hello.mp3"  },
 
{    "name_mp3": "Here I Am",    "link_mp3": "https://archive.org/download/unnokeng-80s/80 Here I Am.mp3"  },
 
{    "name_mp3": "Hit Me With Your Best Shot",    "link_mp3": "https://archive.org/download/unnokeng-80s/46 Hit Me With Your Best Shot.mp3"  },
 
{    "name_mp3": "Hold Me Now",    "link_mp3": "https://archive.org/download/unnokeng-80s/23 Hold Me Now.mp3"  },
 
{    "name_mp3": "Hold On To The Nights",    "link_mp3": "https://archive.org/download/unnokeng-80s/22 Hold On To The Nights.mp3"  },
 
{    "name_mp3": "Holding Back The Years",    "link_mp3": "https://archive.org/download/unnokeng-80s/22 Holding Back The Years.mp3"  },
 
{    "name_mp3": "How About Us",    "link_mp3": "https://archive.org/download/unnokeng-80s/45 How About Us.mp3"  },
 
{    "name_mp3": "How Am I Supposed To Live Without You",    "link_mp3": "https://archive.org/download/unnokeng-80s/61 How Am I Supposed To Live Without You.mp3"  },
 
{    "name_mp3": "How Can I Fall",    "link_mp3": "https://archive.org/download/unnokeng-80s/17 How Can I Fall.mp3"  },
 
{    "name_mp3": "How Can I Fall",    "link_mp3": "https://archive.org/download/unnokeng-80s/27 How Can I Fall.mp3"  },
 
{    "name_mp3": "HowDoIMakeYou",    "link_mp3": "https://archive.org/download/unnokeng-80s/HowDoIMakeYou.mp3"  },
 
{    "name_mp3": "Human",    "link_mp3": "https://archive.org/download/unnokeng-80s/25 Human.mp3"  },
 
{    "name_mp3": "Human Nature",    "link_mp3": "https://archive.org/download/unnokeng-80s/89 Human Nature.mp3"  },
 
{    "name_mp3": "Hungry Like The Wolf",    "link_mp3": "https://archive.org/download/unnokeng-80s/17 Hungry Like The Wolf.mp3"  },
 
{    "name_mp3": "Hurts So Good",    "link_mp3": "https://archive.org/download/unnokeng-80s/08 Hurts So Good.mp3"  },
 
{    "name_mp3": "HurtSoBad",    "link_mp3": "https://archive.org/download/unnokeng-80s/HurtSoBad.mp3"  },
 
{    "name_mp3": "I Can't Go For That",    "link_mp3": "https://archive.org/download/unnokeng-80s/15 I Can't Go For That.mp3"  },
 
{    "name_mp3": "I Can't Stand It",    "link_mp3": "https://archive.org/download/unnokeng-80s/67 I Can't Stand It.mp3"  },
 
{    "name_mp3": "I Can't Tell You Why",    "link_mp3": "https://archive.org/download/unnokeng-80s/62 I Can't Tell You Why.mp3"  },
 
{    "name_mp3": "I Can't Wait",    "link_mp3": "https://archive.org/download/unnokeng-80s/26 I Can't Wait.mp3"  },
 
{    "name_mp3": "I Just Called To Say I Love Yo",    "link_mp3": "https://archive.org/download/unnokeng-80s/25 I Just Called To Say I Love Yo.mp3"  },
 
{    "name_mp3": "I Just Can't Stop Loving You",    "link_mp3": "https://archive.org/download/unnokeng-80s/45 I Just Can't Stop Loving You.mp3"  },
 
{    "name_mp3": "I Just Died In Your Arms Tonight",    "link_mp3": "https://archive.org/download/unnokeng-80s/32 I Just Died In Your Arms Tonight.mp3"  },
 
{    "name_mp3": "I Keep Forgettin'",    "link_mp3": "https://archive.org/download/unnokeng-80s/81 I Keep Forgettin'.mp3"  },
 
{    "name_mp3": "I Love Rock N' Roll",    "link_mp3": "https://archive.org/download/unnokeng-80s/03 I Love Rock N' Roll.mp3"  },
 
{    "name_mp3": "I Love You",    "link_mp3": "https://archive.org/download/unnokeng-80s/20 I Love You.mp3"  },
 
{    "name_mp3": "I Made It Through The Rain",    "link_mp3": "https://archive.org/download/unnokeng-80s/89 I Made It Through The Rain.mp3"  },
 
{    "name_mp3": "I Pledge My Love",    "link_mp3": "https://archive.org/download/unnokeng-80s/80 I Pledge My Love.mp3"  },
 
{    "name_mp3": "I Ran (So Far Away)",    "link_mp3": "https://archive.org/download/unnokeng-80s/67 I Ran (So Far Away).mp3"  },
 
{    "name_mp3": "I Think We're Alone Now",    "link_mp3": "https://archive.org/download/unnokeng-80s/18 I Think We're Alone Now.mp3"  },
 
{    "name_mp3": "I Wanna Be Your Lover",    "link_mp3": "https://archive.org/download/unnokeng-80s/95 I Wanna Be Your Lover.mp3"  },
 
{    "name_mp3": "I Want To Be Your Man",    "link_mp3": "https://archive.org/download/unnokeng-80s/56 I Want To Be Your Man.mp3"  },
 
{    "name_mp3": "I Want to Know What Love Is",    "link_mp3": "https://archive.org/download/unnokeng-80s/04 I Want to Know What Love Is.mp3"  },
 
{    "name_mp3": "I Want to Rock With You",    "link_mp3": "https://archive.org/download/unnokeng-80s/04 I Want to Rock With You.mp3"  },
 
{    "name_mp3": "I Won't Hold You Back",    "link_mp3": "https://archive.org/download/unnokeng-80s/69 I Won't Hold You Back.mp3"  },
 
{    "name_mp3": "If Ever You're In My Arms Again",    "link_mp3": "https://archive.org/download/unnokeng-80s/47 If Ever You're In My Arms Again.mp3"  },
 
{    "name_mp3": "If I Could Turn Back Time",    "link_mp3": "https://archive.org/download/unnokeng-80s/35 If I Could Turn Back Time.mp3"  },
 
{    "name_mp3": "If You Don't Know Me By Now",    "link_mp3": "https://archive.org/download/unnokeng-80s/24 If You Don't Know Me By Now.mp3"  },
 
{    "name_mp3": "If You Leave",    "link_mp3": "https://archive.org/download/unnokeng-80s/53 If You Leave.mp3"  },
 
{    "name_mp3": "I'll Always Love You",    "link_mp3": "https://archive.org/download/unnokeng-80s/I'll Always Love You.mp3.mp3"  },
 
{    "name_mp3": "Ill Be Loving You (Forever)",    "link_mp3": "https://archive.org/download/unnokeng-80s/26 Ill Be Loving You (Forever).mp3"  },
 
{    "name_mp3": "I'll Be Over You",    "link_mp3": "https://archive.org/download/unnokeng-80s/99 I'll Be Over You.mp3"  },
 
{    "name_mp3": "I'll Be There For You",    "link_mp3": "https://archive.org/download/unnokeng-80s/23 I'll Be There For You.mp3"  },
 
{    "name_mp3": "I'm Coming Out",    "link_mp3": "https://archive.org/download/unnokeng-80s/98 I'm Coming Out.mp3"  },
 
{    "name_mp3": "I'm Gonna Miss You",    "link_mp3": "https://archive.org/download/unnokeng-80s/16 I'm Gonna Miss You.mp3"  },
 
{    "name_mp3": "Islands In The Stream [feat Dolly Parton]",    "link_mp3": "https://archive.org/download/unnokeng-80s/56 Islands In The Stream [feat Dolly Parton].mp3"  },
 
{    "name_mp3": "It Might Be You",    "link_mp3": "https://archive.org/download/unnokeng-80s/95 It Might Be You.mp3"  },
 
{    "name_mp3": "It's My Turn",    "link_mp3": "https://archive.org/download/unnokeng-80s/01 It's My Turn.mp3"  },
 
{    "name_mp3": "It's Still Rock and Roll to Me",    "link_mp3": "https://archive.org/download/unnokeng-80s/09 It's Still Rock and Roll to Me.mp3"  },
 
{    "name_mp3": "Jack And Diane",    "link_mp3": "https://archive.org/download/unnokeng-80s/07 Jack And Diane.mp3"  },
 
{    "name_mp3": "Jessie's Girl",    "link_mp3": "https://archive.org/download/unnokeng-80s/05 Jessie's Girl.mp3"  },
 
{    "name_mp3": "Just The Two Of Us",    "link_mp3": "https://archive.org/download/unnokeng-80s/18 Just The Two Of Us.mp3"  },
 
{    "name_mp3": "JustOneLook",    "link_mp3": "https://archive.org/download/unnokeng-80s/JustOneLook.mp3"  },
 
{    "name_mp3": "Karma Chameleon",    "link_mp3": "https://archive.org/download/unnokeng-80s/10 Karma Chameleon.mp3"  },
 
{    "name_mp3": "Keep On Loving You",    "link_mp3": "https://archive.org/download/unnokeng-80s/10 Keep On Loving You.mp3"  },
 
{    "name_mp3": "Kiss",    "link_mp3": "https://archive.org/download/unnokeng-80s/19 Kiss.mp3"  },
 
{    "name_mp3": "Kiss Is On My List",    "link_mp3": "https://archive.org/download/unnokeng-80s/07 Kiss Is On My List.mp3"  },
 
{    "name_mp3": "Kokomo",    "link_mp3": "https://archive.org/download/unnokeng-80s/44 Kokomo.mp3"  },
 
{    "name_mp3": "Ladies Night",    "link_mp3": "https://archive.org/download/unnokeng-80s/35 Ladies Night.mp3"  },
 
{    "name_mp3": "Lady",    "link_mp3": "https://archive.org/download/unnokeng-80s/03 Lady.mp3"  },
 
{    "name_mp3": "Leader Of The Band",    "link_mp3": "https://archive.org/download/unnokeng-80s/35 Leader Of The Band.mp3"  },
 
{    "name_mp3": "Lean On Me",    "link_mp3": "https://archive.org/download/unnokeng-80s/29 Lean On Me.mp3"  },
 
{    "name_mp3": "Let's Go Crazy",    "link_mp3": "https://archive.org/download/unnokeng-80s/21 Let's Go Crazy.mp3"  },
 
{    "name_mp3": "Let's Groove",    "link_mp3": "https://archive.org/download/unnokeng-80s/33 Let's Groove.mp3"  },
 
{    "name_mp3": "Let's Hear It For The Boy",    "link_mp3": "https://archive.org/download/unnokeng-80s/13 Let's Hear It For The Boy.mp3"  },
 
{    "name_mp3": "Like A Prayer",    "link_mp3": "https://archive.org/download/unnokeng-80s/25 Like A Prayer.mp3"  },
 
{    "name_mp3": "Like a Virgin",    "link_mp3": "https://archive.org/download/unnokeng-80s/02 Like a Virgin.mp3"  },
 
{    "name_mp3": "Listen To Your Heart",    "link_mp3": "https://archive.org/download/unnokeng-80s/22 Listen To Your Heart.mp3"  },
 
{    "name_mp3": "Little Jeannie",    "link_mp3": "https://archive.org/download/unnokeng-80s/16 Little Jeannie.mp3"  },
 
{    "name_mp3": "Little Red Corvette",    "link_mp3": "https://archive.org/download/unnokeng-80s/25 Little Red Corvette.mp3"  },
 
{    "name_mp3": "Live To Tell",    "link_mp3": "https://archive.org/download/unnokeng-80s/35 Live To Tell.mp3"  },
 
{    "name_mp3": "Livin' On A Prayer",    "link_mp3": "https://archive.org/download/unnokeng-80s/10 Livin' On A Prayer.mp3"  },
 
{    "name_mp3": "Longer Than",    "link_mp3": "https://archive.org/download/unnokeng-80s/33 Longer Than.mp3"  },
 
{    "name_mp3": "Look Away",    "link_mp3": "https://archive.org/download/unnokeng-80s/01 Look Away.mp3"  },
 
{    "name_mp3": "Lost In Love",    "link_mp3": "https://archive.org/download/unnokeng-80s/15 Lost In Love.mp3"  },
 
{    "name_mp3": "Lost In Your Eyes",    "link_mp3": "https://archive.org/download/unnokeng-80s/13 Lost In Your Eyes.mp3"  },
 
{    "name_mp3": "Love Bites",    "link_mp3": "https://archive.org/download/unnokeng-80s/24 Love Bites.mp3"  },
 
{    "name_mp3": "Love Is A Battlefield",    "link_mp3": "https://archive.org/download/unnokeng-80s/57 Love Is A Battlefield.mp3"  },
 
{    "name_mp3": "Love Shack",    "link_mp3": "https://archive.org/download/unnokeng-80s/47 Love Shack.mp3"  },
 
{    "name_mp3": "Love Song",    "link_mp3": "https://archive.org/download/unnokeng-80s/68 Love Song.mp3"  },
 
{    "name_mp3": "Luka",    "link_mp3": "https://archive.org/download/unnokeng-80s/52 Luka.mp3"  },
 
{    "name_mp3": "Making Love",    "link_mp3": "https://archive.org/download/unnokeng-80s/46 Making Love.mp3"  },
 
{    "name_mp3": "Making Love Out Of Nothing At All",    "link_mp3": "https://archive.org/download/unnokeng-80s/66 Making Love Out Of Nothing At All.mp3"  },
 
{    "name_mp3": "Man In The Mirror",    "link_mp3": "https://archive.org/download/unnokeng-80s/23 Man In The Mirror.mp3"  },
 
{    "name_mp3": "Maneater",    "link_mp3": "https://archive.org/download/unnokeng-80s/07 Maneater.mp3"  },
 
{    "name_mp3": "Manic Monday",    "link_mp3": "https://archive.org/download/unnokeng-80s/48 Manic Monday.mp3"  },
 
{    "name_mp3": "Material Girl",    "link_mp3": "https://archive.org/download/unnokeng-80s/58 Material Girl.mp3"  },
 
{    "name_mp3": "Meet Me Halfway",    "link_mp3": "https://archive.org/download/unnokeng-80s/96 Meet Me Halfway.mp3"  },
 
{    "name_mp3": "Method Of Modern Love",    "link_mp3": "https://archive.org/download/unnokeng-80s/83 Method Of Modern Love.mp3"  },
 
{    "name_mp3": "Mickey",    "link_mp3": "https://archive.org/download/unnokeng-80s/36 Mickey.mp3"  },
 
{    "name_mp3": "Miss You Like Crazy",    "link_mp3": "https://archive.org/download/unnokeng-80s/67 Miss You Like Crazy.mp3"  },
 
{    "name_mp3": "Missing You",    "link_mp3": "https://archive.org/download/unnokeng-80s/11 Missing You.mp3"  },
 
{    "name_mp3": "Mony Mony",    "link_mp3": "https://archive.org/download/unnokeng-80s/19 Mony Mony.mp3"  },
 
{    "name_mp3": "Mr Roboto",    "link_mp3": "https://archive.org/download/unnokeng-80s/28 Mr Roboto.mp3"  },
 
{    "name_mp3": "My Love",    "link_mp3": "https://archive.org/download/unnokeng-80s/73 My Love.mp3"  },
 
{    "name_mp3": "My Perogative",    "link_mp3": "https://archive.org/download/unnokeng-80s/02 My Perogative.mp3"  },
 
{    "name_mp3": "Never Gonna Give You Up",    "link_mp3": "https://archive.org/download/unnokeng-80s/10 Never Gonna Give You Up.mp3"  },
 
{    "name_mp3": "Never Gonna Let You Go",    "link_mp3": "https://archive.org/download/unnokeng-80s/16 Never Gonna Let You Go.mp3"  },
 
{    "name_mp3": "No More Lonely Nights",    "link_mp3": "https://archive.org/download/unnokeng-80s/72 No More Lonely Nights.mp3"  },
 
{    "name_mp3": "No More Lonely Nights",    "link_mp3": "https://archive.org/download/unnokeng-80s/94 No More Lonely Nights.mp3"  },
 
{    "name_mp3": "No More Tears (Enough is Enough) [feat Donna Summer]",    "link_mp3": "https://archive.org/download/unnokeng-80s/38 No More Tears (Enough is Enough) [feat Donna Summer].mp3"  },
 
{    "name_mp3": "Nothing's Gonna Change My Love",    "link_mp3": "https://archive.org/download/unnokeng-80s/85 Nothing's Gonna Change My Love.mp3"  },
 
{    "name_mp3": "Nothing's Gonna Stop Us Now",    "link_mp3": "https://archive.org/download/unnokeng-80s/05 Nothing's Gonna Stop Us Now.mp3"  },
 
{    "name_mp3": "Notorious",    "link_mp3": "https://archive.org/download/unnokeng-80s/25 Notorious.mp3"  },
 
{    "name_mp3": "Oh, Sherrie",    "link_mp3": "https://archive.org/download/unnokeng-80s/31 Oh%2C Sherrie.mp3"  },
 
{    "name_mp3": "On My Own [feat Michael McDonald]",    "link_mp3": "https://archive.org/download/unnokeng-80s/04 On My Own [feat Michael McDonald].mp3"  },
 
{    "name_mp3": "On Our Own",    "link_mp3": "https://archive.org/download/unnokeng-80s/19 On Our Own.mp3"  },
 
{    "name_mp3": "One Hundred Ways",    "link_mp3": "https://archive.org/download/unnokeng-80s/61 One Hundred Ways.mp3"  },
 
{    "name_mp3": "One More Night",    "link_mp3": "https://archive.org/download/unnokeng-80s/33 One More Night.mp3"  },
 
{    "name_mp3": "One More Try",    "link_mp3": "https://archive.org/download/unnokeng-80s/26 One More Try.mp3"  },
 
{    "name_mp3": "One Night In Bangkok",    "link_mp3": "https://archive.org/download/unnokeng-80s/54 One Night In Bangkok.mp3"  },
 
{    "name_mp3": "One On One",    "link_mp3": "https://archive.org/download/unnokeng-80s/39 One On One.mp3"  },
 
{    "name_mp3": "Only The Lonely",    "link_mp3": "https://archive.org/download/unnokeng-80s/29 Only The Lonely.mp3"  },
 
{    "name_mp3": "Open Arms",    "link_mp3": "https://archive.org/download/unnokeng-80s/34 Open Arms.mp3"  },
 
{    "name_mp3": "Out of Touch",    "link_mp3": "https://archive.org/download/unnokeng-80s/06 Out of Touch.mp3"  },
 
{    "name_mp3": "Owner Of A Lonely Heart",    "link_mp3": "https://archive.org/download/unnokeng-80s/08 Owner Of A Lonely Heart.mp3"  },
 
{    "name_mp3": "Papa Don't Preach",    "link_mp3": "https://archive.org/download/unnokeng-80s/29 Papa Don't Preach.mp3"  },
 
{    "name_mp3": "Paradise City",    "link_mp3": "https://archive.org/download/unnokeng-80s/86 Paradise City.mp3"  },
 
{    "name_mp3": "Part-Time Lover",    "link_mp3": "https://archive.org/download/unnokeng-80s/22 Part-Time Lover.mp3"  },
 
{    "name_mp3": "Patience",    "link_mp3": "https://archive.org/download/unnokeng-80s/71 Patience.mp3"  },
 
{    "name_mp3": "Photograph",    "link_mp3": "https://archive.org/download/unnokeng-80s/90 Photograph.mp3"  },
 
{    "name_mp3": "Physical",    "link_mp3": "https://archive.org/download/unnokeng-80s/01 Physical.mp3"  },
 
{    "name_mp3": "Pilot Of The Airwaves",    "link_mp3": "https://archive.org/download/unnokeng-80s/77 Pilot Of The Airwaves.mp3"  },
 
{    "name_mp3": "Please Don't Go",    "link_mp3": "https://archive.org/download/unnokeng-80s/19 Please Don't Go.mp3"  },
 
{    "name_mp3": "Pour Some Sugar On Me",    "link_mp3": "https://archive.org/download/unnokeng-80s/32 Pour Some Sugar On Me.mp3"  },
 
{    "name_mp3": "Private Dancer",    "link_mp3": "https://archive.org/download/unnokeng-80s/93 Private Dancer.mp3"  },
 
{    "name_mp3": "Private Eyes",    "link_mp3": "https://archive.org/download/unnokeng-80s/44 Private Eyes.mp3"  },
 
{    "name_mp3": "Raspberry Beret",    "link_mp3": "https://archive.org/download/unnokeng-80s/51 Raspberry Beret.mp3"  },
 
{    "name_mp3": "Red Red Wine",    "link_mp3": "https://archive.org/download/unnokeng-80s/42 Red Red Wine.mp3"  },
 
{    "name_mp3": "RescueMe",    "link_mp3": "https://archive.org/download/unnokeng-80s/RescueMe.mp3"  },
 
{    "name_mp3": "Rhythm of the Night",    "link_mp3": "https://archive.org/download/unnokeng-80s/32 Rhythm of the Night.mp3"  },
 
{    "name_mp3": "Ride Like the Wind",    "link_mp3": "https://archive.org/download/unnokeng-80s/17 Ride Like the Wind.mp3"  },
 
{    "name_mp3": "Right Here Waiting",    "link_mp3": "https://archive.org/download/unnokeng-80s/11 Right Here Waiting.mp3"  },
 
{    "name_mp3": "Rock Steady",    "link_mp3": "https://archive.org/download/unnokeng-80s/73 Rock Steady.mp3"  },
 
{    "name_mp3": "Rosanna",    "link_mp3": "https://archive.org/download/unnokeng-80s/14 Rosanna.mp3"  },
 
{    "name_mp3": "Run To You",    "link_mp3": "https://archive.org/download/unnokeng-80s/66 Run To You.mp3"  },
 
{    "name_mp3": "Running With The Night",    "link_mp3": "https://archive.org/download/unnokeng-80s/53 Running With The Night.mp3"  },
 
{    "name_mp3": "Sailing",    "link_mp3": "https://archive.org/download/unnokeng-80s/32 Sailing.mp3"  },
 
{    "name_mp3": "Same Old Lang Syne",    "link_mp3": "https://archive.org/download/unnokeng-80s/79 Same Old Lang Syne.mp3"  },
 
{    "name_mp3": "Sara",    "link_mp3": "https://archive.org/download/unnokeng-80s/24 Sara.mp3"  },
 
{    "name_mp3": "Satisfied",    "link_mp3": "https://archive.org/download/unnokeng-80s/54 Satisfied.mp3"  },
 
{    "name_mp3": "Saving All My Love for You",    "link_mp3": "https://archive.org/download/unnokeng-80s/23 Saving All My Love for You.mp3"  },
 
{    "name_mp3": "Say It Isn't So",    "link_mp3": "https://archive.org/download/unnokeng-80s/22 Say It Isn't So.mp3"  },
 
{    "name_mp3": "Say You, Say Me",    "link_mp3": "https://archive.org/download/unnokeng-80s/02 Say You%2C Say Me.mp3"  },
 
{    "name_mp3": "Say, Say, Say [feat Michael Jackson]",    "link_mp3": "https://archive.org/download/unnokeng-80s/03 Say%2C Say%2C Say [feat Michael Jackson].mp3"  },
 
{    "name_mp3": "Secret Lovers",    "link_mp3": "https://archive.org/download/unnokeng-80s/12 Secret Lovers.mp3"  },
 
{    "name_mp3": "Send One Your Love",    "link_mp3": "https://archive.org/download/unnokeng-80s/43 Send One Your Love.mp3"  },
 
{    "name_mp3": "Separate Ways (Worlds Apart)",    "link_mp3": "https://archive.org/download/unnokeng-80s/38 Separate Ways (Worlds Apart).mp3"  },
 
{    "name_mp3": "Sexual Healing",    "link_mp3": "https://archive.org/download/unnokeng-80s/32 Sexual Healing.mp3"  },
 
{    "name_mp3": "Shattered Dreams",    "link_mp3": "https://archive.org/download/unnokeng-80s/46 Shattered Dreams.mp3"  },
 
{    "name_mp3": "She Drives Me Crazy",    "link_mp3": "https://archive.org/download/unnokeng-80s/18 She Drives Me Crazy.mp3"  },
 
{    "name_mp3": "She Works Hard For The Money",    "link_mp3": "https://archive.org/download/unnokeng-80s/15 She Works Hard For The Money.mp3"  },
 
{    "name_mp3": "Shining Shining Star",    "link_mp3": "https://archive.org/download/unnokeng-80s/22 Shining Shining Star.mp3"  },
 
{    "name_mp3": "Shout",    "link_mp3": "https://archive.org/download/unnokeng-80s/21 Shout.mp3"  },
 
{    "name_mp3": "Smooth Criminal",    "link_mp3": "https://archive.org/download/unnokeng-80s/93 Smooth Criminal.mp3"  },
 
{    "name_mp3": "Smooth Operator",    "link_mp3": "https://archive.org/download/unnokeng-80s/62 Smooth Operator.mp3"  },
 
{    "name_mp3": "Somebody's Watching Me",    "link_mp3": "https://archive.org/download/unnokeng-80s/26 Somebody's Watching Me.mp3"  },
 
{    "name_mp3": "Somewhere Out There",    "link_mp3": "https://archive.org/download/unnokeng-80s/39 Somewhere Out There.mp3"  },
 
{    "name_mp3": "SomewhereOutTherefeatJamesIngram",    "link_mp3": "https://archive.org/download/unnokeng-80s/SomewhereOutTherefeatJamesIngram.mp3"  },
 
{    "name_mp3": "Sowing The Seeds Of Love",    "link_mp3": "https://archive.org/download/unnokeng-80s/58 Sowing The Seeds Of Love.mp3"  },
 
{    "name_mp3": "Stand By Me",    "link_mp3": "https://archive.org/download/unnokeng-80s/67 Stand By Me.mp3"  },
 
{    "name_mp3": "State Of Shock [feat Mick Jagger]",    "link_mp3": "https://archive.org/download/unnokeng-80s/61 State Of Shock [feat Mick Jagger].mp3"  },
 
{    "name_mp3": "Steal Away",    "link_mp3": "https://archive.org/download/unnokeng-80s/26 Steal Away.mp3"  },
 
{    "name_mp3": "Straight From the Heart",    "link_mp3": "https://archive.org/download/unnokeng-80s/71 Straight From the Heart.mp3"  },
 
{    "name_mp3": "Straight Up",    "link_mp3": "https://archive.org/download/unnokeng-80s/04 Straight Up.mp3"  },
 
{    "name_mp3": "Stuck On You",    "link_mp3": "https://archive.org/download/unnokeng-80s/32 Stuck On You.mp3"  },
 
{    "name_mp3": "Suddenly",    "link_mp3": "https://archive.org/download/unnokeng-80s/52 Suddenly.mp3"  },
 
{    "name_mp3": "Sukiyaki",    "link_mp3": "https://archive.org/download/unnokeng-80s/22 Sukiyaki.mp3"  },
 
{    "name_mp3": "Summer Of '69",    "link_mp3": "https://archive.org/download/unnokeng-80s/74 Summer Of '69.mp3"  },
 
{    "name_mp3": "Sunglasses At Night",    "link_mp3": "https://archive.org/download/unnokeng-80s/36 Sunglasses At Night.mp3"  },
 
{    "name_mp3": "Surrender To Me [feat Robin Zander]",    "link_mp3": "https://archive.org/download/unnokeng-80s/98 Surrender To Me [feat Robin Zander].mp3"  },
 
{    "name_mp3": "Sweet Child O' Mine",    "link_mp3": "https://archive.org/download/unnokeng-80s/11 Sweet Child O' Mine.mp3"  },
 
{    "name_mp3": "Sweet Dreams",    "link_mp3": "https://archive.org/download/unnokeng-80s/28 Sweet Dreams.mp3"  },
 
{    "name_mp3": "Sweet Dreams (Are Made Of This)",    "link_mp3": "https://archive.org/download/unnokeng-80s/10 Sweet Dreams (Are Made Of This).mp3"  },
 
{    "name_mp3": "Tainted Love 1",    "link_mp3": "https://archive.org/download/unnokeng-80s/11 Tainted Love 1.mp3"  },
 
{    "name_mp3": "Take It On The Run",    "link_mp3": "https://archive.org/download/unnokeng-80s/32 Take It On The Run.mp3"  },
 
{    "name_mp3": "Take My Breath Away",    "link_mp3": "https://archive.org/download/unnokeng-80s/27 Take My Breath Away.mp3"  },
 
{    "name_mp3": "Take on Me",    "link_mp3": "https://archive.org/download/unnokeng-80s/10 Take on Me.mp3"  },
 
{    "name_mp3": "Talking In Your Sleep",    "link_mp3": "https://archive.org/download/unnokeng-80s/19 Talking In Your Sleep.mp3"  },
 
{    "name_mp3": "Tell Her About It",    "link_mp3": "https://archive.org/download/unnokeng-80s/45 Tell Her About It.mp3"  },
 
{    "name_mp3": "Tell It To My Heart",    "link_mp3": "https://archive.org/download/unnokeng-80s/41 Tell It To My Heart.mp3"  },
 
{    "name_mp3": "TellHim",    "link_mp3": "https://archive.org/download/unnokeng-80s/TellHim.mp3"  },
 
{    "name_mp3": "That Girl",    "link_mp3": "https://archive.org/download/unnokeng-80s/43 That Girl.mp3"  },
 
{    "name_mp3": "That's What Friends Are For",    "link_mp3": "https://archive.org/download/unnokeng-80s/01 That's What Friends Are For.mp3"  },
 
{    "name_mp3": "The Best Of Times",    "link_mp3": "https://archive.org/download/unnokeng-80s/30 The Best Of Times.mp3"  },
 
{    "name_mp3": "The Breakup Song",    "link_mp3": "https://archive.org/download/unnokeng-80s/47 The Breakup Song.mp3"  },
 
{    "name_mp3": "The Girl Is Mine",    "link_mp3": "https://archive.org/download/unnokeng-80s/49 The Girl Is Mine.mp3"  },
 
{    "name_mp3": "The Heat Is On",    "link_mp3": "https://archive.org/download/unnokeng-80s/19 The Heat Is On.mp3"  },
 
{    "name_mp3": "The Lady In Red",    "link_mp3": "https://archive.org/download/unnokeng-80s/21 The Lady In Red.mp3"  },
 
{    "name_mp3": "The Locomotion",    "link_mp3": "https://archive.org/download/unnokeng-80s/51 The Locomotion.mp3"  },
 
{    "name_mp3": "The Look",    "link_mp3": "https://archive.org/download/unnokeng-80s/17 The Look.mp3"  },
 
{    "name_mp3": "The Next Time I Fall",    "link_mp3": "https://archive.org/download/unnokeng-80s/28 The Next Time I Fall.mp3"  },
 
{    "name_mp3": "The One That You Love",    "link_mp3": "https://archive.org/download/unnokeng-80s/28 The One That You Love.mp3"  },
 
{    "name_mp3": "The Other Woman",    "link_mp3": "https://archive.org/download/unnokeng-80s/26 The Other Woman.mp3"  },
 
{    "name_mp3": "The Promise",    "link_mp3": "https://archive.org/download/unnokeng-80s/84 The Promise.mp3"  },
 
{    "name_mp3": "The Second Time Around",    "link_mp3": "https://archive.org/download/unnokeng-80s/44 The Second Time Around.mp3"  },
 
{    "name_mp3": "The Sweetest Thing (I've Ever Known)",    "link_mp3": "https://archive.org/download/unnokeng-80s/21 The Sweetest Thing (I've Ever Known).mp3"  },
 
{    "name_mp3": "The Way It Is",    "link_mp3": "https://archive.org/download/unnokeng-80s/08 The Way It Is.mp3"  },
 
{    "name_mp3": "The Way You Make Me Feel",    "link_mp3": "https://archive.org/download/unnokeng-80s/39 The Way You Make Me Feel.mp3"  },
 
{    "name_mp3": "There'll Be Sad Songs",    "link_mp3": "https://archive.org/download/unnokeng-80s/16 There'll Be Sad Songs.mp3"  },
 
{    "name_mp3": "This Is It",    "link_mp3": "https://archive.org/download/unnokeng-80s/28 This Is It.mp3"  },
 
{    "name_mp3": "Time After Time",    "link_mp3": "https://archive.org/download/unnokeng-80s/17 Time After Time.mp3"  },
 
{    "name_mp3": "To All The Girls I've Loved Before [feat Willi Nelson]",    "link_mp3": "https://archive.org/download/unnokeng-80s/50 To All The Girls I've Loved Before [feat Willi Nelson].mp3"  },
 
{    "name_mp3": "Tonight, I Celebrate My Love",    "link_mp3": "https://archive.org/download/unnokeng-80s/96 Tonight%2C I Celebrate My Love.mp3"  },
 
{    "name_mp3": "Too Hot",    "link_mp3": "https://archive.org/download/unnokeng-80s/36 Too Hot.mp3"  },
 
{    "name_mp3": "Total Eclipse Of The Heart",    "link_mp3": "https://archive.org/download/unnokeng-80s/06 Total Eclipse Of The Heart.mp3"  },
 
{    "name_mp3": "Toy Soldiers",    "link_mp3": "https://archive.org/download/unnokeng-80s/29 Toy Soldiers.mp3"  },
 
{    "name_mp3": "True",    "link_mp3": "https://archive.org/download/unnokeng-80s/92 True.mp3"  },
 
{    "name_mp3": "True Colors",    "link_mp3": "https://archive.org/download/unnokeng-80s/41 True Colors.mp3"  },
 
{    "name_mp3": "Two Hearts",    "link_mp3": "https://archive.org/download/unnokeng-80s/20 Two Hearts.mp3"  },
 
{    "name_mp3": "Uptown Girl",    "link_mp3": "https://archive.org/download/unnokeng-80s/39 Uptown Girl.mp3"  },
 
{    "name_mp3": "Vacation",    "link_mp3": "https://archive.org/download/unnokeng-80s/87 Vacation.mp3"  },
 
{    "name_mp3": "Venus",    "link_mp3": "https://archive.org/download/unnokeng-80s/38 Venus.mp3"  },
 
{    "name_mp3": "Voices Carry",    "link_mp3": "https://archive.org/download/unnokeng-80s/68 Voices Carry.mp3"  },
 
{    "name_mp3": "Waiting For A Girl Like You",    "link_mp3": "https://archive.org/download/unnokeng-80s/19 Waiting For A Girl Like You.mp3"  },
 
{    "name_mp3": "Walk This Way",    "link_mp3": "https://archive.org/download/unnokeng-80s/89 Walk This Way.mp3"  },
 
{    "name_mp3": "Walking On Sunshine",    "link_mp3": "https://archive.org/download/unnokeng-80s/75 Walking On Sunshine.mp3"  },
 
{    "name_mp3": "Wanna Be Startin' Somethin'",    "link_mp3": "https://archive.org/download/unnokeng-80s/68 Wanna Be Startin' Somethin'.mp3"  },
 
{    "name_mp3": "Wanted Dead Or Alive",    "link_mp3": "https://archive.org/download/unnokeng-80s/74 Wanted Dead Or Alive.mp3"  },
 
{    "name_mp3": "We Are the World",    "link_mp3": "https://archive.org/download/unnokeng-80s/20 We Are the World.mp3"  },
 
{    "name_mp3": "We Belong",    "link_mp3": "https://archive.org/download/unnokeng-80s/39 We Belong.mp3"  },
 
{    "name_mp3": "We Built This City",    "link_mp3": "https://archive.org/download/unnokeng-80s/14 We Built This City.mp3"  },
 
{    "name_mp3": "We Got The Beat",    "link_mp3": "https://archive.org/download/unnokeng-80s/25 We Got The Beat.mp3"  },
 
{    "name_mp3": "Welcome To The Jungle",    "link_mp3": "https://archive.org/download/unnokeng-80s/71 Welcome To The Jungle.mp3"  },
 
{    "name_mp3": "We've Got Tonight",    "link_mp3": "https://archive.org/download/unnokeng-80s/40 We've Got Tonight.mp3"  },
 
{    "name_mp3": "What About Love",    "link_mp3": "https://archive.org/download/unnokeng-80s/87 What About Love.mp3"  },
 
{    "name_mp3": "What Are We Doing In Love [feat Dottie West]",    "link_mp3": "https://archive.org/download/unnokeng-80s/55 What Are We Doing In Love [feat Dottie West].mp3"  },
 
{    "name_mp3": "What I Am",    "link_mp3": "https://archive.org/download/unnokeng-80s/84 What I Am.mp3"  },
 
{    "name_mp3": "What Kind Of Fool [feat Barry Gibb]",    "link_mp3": "https://archive.org/download/unnokeng-80s/85 What Kind Of Fool [feat Barry Gibb].mp3"  },
 
{    "name_mp3": "What's Love Got To Do With It",    "link_mp3": "https://archive.org/download/unnokeng-80s/02 What's Love Got To Do With It.mp3"  },
 
{    "name_mp3": "When Doves Cry",    "link_mp3": "https://archive.org/download/unnokeng-80s/01 When Doves Cry.mp3"  },
 
{    "name_mp3": "When I See You Smile",    "link_mp3": "https://archive.org/download/unnokeng-80s/34 When I See You Smile.mp3"  },
 
{    "name_mp3": "When I Think Of You",    "link_mp3": "https://archive.org/download/unnokeng-80s/32 When I Think Of You.mp3"  },
 
{    "name_mp3": "Where Do Broken Hearts Go",    "link_mp3": "https://archive.org/download/unnokeng-80s/25 Where Do Broken Hearts Go.mp3"  },
 
{    "name_mp3": "Who Can It Be Now",    "link_mp3": "https://archive.org/download/unnokeng-80s/30 Who Can It Be Now.mp3"  },
 
{    "name_mp3": "Who's Crying Now",    "link_mp3": "https://archive.org/download/unnokeng-80s/56 Who's Crying Now.mp3"  },
 
{    "name_mp3": "Why Do Fools Fall In Love",    "link_mp3": "https://archive.org/download/unnokeng-80s/54 Why Do Fools Fall In Love.mp3"  },
 
{    "name_mp3": "Wind Beneath My Wings",    "link_mp3": "https://archive.org/download/unnokeng-80s/07 Wind Beneath My Wings.mp3"  },
 
{    "name_mp3": "With Or Without You",    "link_mp3": "https://archive.org/download/unnokeng-80s/15 With Or Without You.mp3"  },
 
{    "name_mp3": "Woman",    "link_mp3": "https://archive.org/download/unnokeng-80s/21 Woman.mp3"  },
 
{    "name_mp3": "Woman In Love",    "link_mp3": "https://archive.org/download/unnokeng-80s/35 Woman In Love.mp3"  },
 
{    "name_mp3": "Word Up",    "link_mp3": "https://archive.org/download/unnokeng-80s/68 Word Up.mp3"  },
 
{    "name_mp3": "Words Get In The Way",    "link_mp3": "https://archive.org/download/unnokeng-80s/47 Words Get In The Way.mp3"  },
 
{    "name_mp3": "You And I",    "link_mp3": "https://archive.org/download/unnokeng-80s/12 You And I.mp3"  },
 
{    "name_mp3": "You Can Do Magic",    "link_mp3": "https://archive.org/download/unnokeng-80s/65 You Can Do Magic.mp3"  },
 
{    "name_mp3": "You Can't Hurry Love",    "link_mp3": "https://archive.org/download/unnokeng-80s/37 You Can't Hurry Love.mp3"  },
 
{    "name_mp3": "You Deccorated My Life",    "link_mp3": "https://archive.org/download/unnokeng-80s/93 You Deccorated My Life.mp3"  },
 
{    "name_mp3": "You Give Love A Bad Name",    "link_mp3": "https://archive.org/download/unnokeng-80s/30 You Give Love A Bad Name.mp3"  },
 
{    "name_mp3": "You Got It All",    "link_mp3": "https://archive.org/download/unnokeng-80s/43 You Got It All.mp3"  },
 
{    "name_mp3": "You Keep Me Hangin' On",    "link_mp3": "https://archive.org/download/unnokeng-80s/34 You Keep Me Hangin' On.mp3"  },
 
{    "name_mp3": "You Make My Dreams",    "link_mp3": "https://archive.org/download/unnokeng-80s/43 You Make My Dreams.mp3"  },
 
{    "name_mp3": "You Maybe Right",    "link_mp3": "https://archive.org/download/unnokeng-80s/75 You Maybe Right.mp3"  },
 
{    "name_mp3": "Your Love",    "link_mp3": "https://archive.org/download/unnokeng-80s/62 Your Love.mp3"  },
 
{    "name_mp3": "You're the Inspiration",    "link_mp3": "https://archive.org/download/unnokeng-80s/37 You're the Inspiration.mp3"  },
 
{    "name_mp3": "YoureNoGood",    "link_mp3": "https://archive.org/download/unnokeng-80s/YoureNoGood.mp3"  },
 
{    "name_mp3": "You've Lost That Lovin' Feeling",    "link_mp3": "https://archive.org/download/unnokeng-80s/90 You've Lost That Lovin' Feeling.mp3"  }
 




]
}
